dart.py
mseep_dart_mcp_test-0.1.1.dist-info/METADATA
mseep_dart_mcp_test-0.1.1.dist-info/WHEEL
mseep_dart_mcp_test-0.1.1.dist-info/top_level.txt
mseep_dart_mcp_test-0.1.1.dist-info/RECORD
